allen1989/__init__.py
allen1989/info.py
allen1989/raw.py
allen1989/transfer.py
allen1989/version.py
allen1989/clean/readme.rst
allen1989-0.2.0.dist-info/AUTHORS.rst
allen1989-0.2.0.dist-info/LICENSE
allen1989-0.2.0.dist-info/METADATA
allen1989-0.2.0.dist-info/WHEEL
allen1989-0.2.0.dist-info/top_level.txt
allen1989-0.2.0.dist-info/RECORD
