Metadata-Version: 2.1
Name: allen1989
Version: 0.2.0
Summary: Formalisms from Allen at al. 1989 paper
Author-email: revesansparole <revesansparole@gmail.com>
Maintainer-email: revesansparole <revesansparole@gmail.com>, Jerome Chopard <revesansparole@gmail.com>
License: cc_by_nc
Project-URL: repository, https://gitlab.com/b326/allen1989
Project-URL: pip, https://pypi.org/project/allen1989/0.2.0/
Project-URL: conda, https://anaconda.org/revesansparole/allen1989
Project-URL: doc, https://b326.gitlab.io/allen1989/
Project-URL: pypi, https://badge.fury.io/py/allen1989
Classifier: Development Status :: 2 - Pre-Alpha
Classifier: Intended Audience :: Developers
Classifier: License :: OSI Approved :: BSD License
Classifier: Natural Language :: English
Classifier: Programming Language :: Python
Classifier: Programming Language :: Python :: 3
Classifier: Programming Language :: Python :: 3 :: Only
Classifier: Programming Language :: Python :: 3.12
Classifier: Programming Language :: Python :: 3.9
Requires-Python: >=3.9
License-File: LICENSE
License-File: AUTHORS.rst
Provides-Extra: doc
Requires-Dist: sphinx ; extra == 'doc'
Requires-Dist: sphinx-gallery ; extra == 'doc'
Requires-Dist: sphinx-rtd-theme ; extra == 'doc'
Provides-Extra: dvlpt
Requires-Dist: twine ; extra == 'dvlpt'
Provides-Extra: example
Requires-Dist: matplotlib ; extra == 'example'
Requires-Dist: numpy ; extra == 'example'
Provides-Extra: test
Requires-Dist: coverage ; extra == 'test'
Requires-Dist: pytest ; extra == 'test'
Requires-Dist: pytest-cov ; extra == 'test'
Requires-Dist: pytest-mock ; extra == 'test'
